incus/__init__.py
incus/geo.py
incus-0.0.dist-info/LICENSE
incus-0.0.dist-info/METADATA
incus-0.0.dist-info/WHEEL
incus-0.0.dist-info/top_level.txt
incus-0.0.dist-info/RECORD
