Metadata-Version: 2.1
Name: incus
Version: 0.0
Summary: Acoustic FDTD Simulator
Author-email: Ali Hakim Taskiran <alihakimxyz@gmail.com>
License: GNU GENERAL PUBLIC LICENSE
Project-URL: Homepage, https://github.com/alihakimtaskiran/Incus
Project-URL: Bug Tracker, https://github.com/alihakimtaskiran/Incus/issues
Classifier: Programming Language :: Python :: 3
Classifier: License :: OSI Approved :: GNU General Public License v3 (GPLv3)
Classifier: Operating System :: OS Independent
Requires-Python: >=3.7
License-File: LICENSE
